QianduanNeicanFix1/README.md
QianduanNeicanFix1/__init__.py
QianduanNeicanFix1/__main__.py
QianduanNeicanFix1/file.epub
QianduanNeicanFix1/index.html
QianduanNeicanFix1/css/__init__.py
QianduanNeicanFix1/css/annotations.css
QianduanNeicanFix1/css/main.css
QianduanNeicanFix1/css/normalize.css
QianduanNeicanFix1/css/popup.css
QianduanNeicanFix1/font/__init__.py
QianduanNeicanFix1/font/fontello.eot
QianduanNeicanFix1/font/fontello.svg
QianduanNeicanFix1/font/fontello.ttf
QianduanNeicanFix1/font/fontello.woff
QianduanNeicanFix1/img/__init__.py
QianduanNeicanFix1/img/annotator-glyph-sprite.png
QianduanNeicanFix1/img/annotator-icon-sprite.png
QianduanNeicanFix1/img/apple-touch-icon.png
QianduanNeicanFix1/img/cancelfullscreen.png
QianduanNeicanFix1/img/close.png
QianduanNeicanFix1/img/fullscreen.png
QianduanNeicanFix1/img/loader.gif
QianduanNeicanFix1/img/menu-icon.png
QianduanNeicanFix1/img/save.png
QianduanNeicanFix1/img/saved.png
QianduanNeicanFix1/img/settings-s.png
QianduanNeicanFix1/img/settings.png
QianduanNeicanFix1/img/star.png
QianduanNeicanFix1/js/__init__.py
QianduanNeicanFix1/js/epub.js
QianduanNeicanFix1/js/epub.min.js
QianduanNeicanFix1/js/epub.min.map
QianduanNeicanFix1/js/hooks.min.js
QianduanNeicanFix1/js/hooks.min.map
QianduanNeicanFix1/js/reader.js
QianduanNeicanFix1/js/reader.js.map
QianduanNeicanFix1/js/reader.min.js
QianduanNeicanFix1/js/reader.min.map
QianduanNeicanFix1/js/hooks/__init__.py
QianduanNeicanFix1/js/hooks/extensions/__init__.py
QianduanNeicanFix1/js/hooks/extensions/highlight.js
QianduanNeicanFix1/js/libs/__init__.py
QianduanNeicanFix1/js/libs/jquery.min.js
QianduanNeicanFix1/js/libs/localforage.min.js
QianduanNeicanFix1/js/libs/screenfull.js
QianduanNeicanFix1/js/libs/screenfull.min.js
QianduanNeicanFix1/js/libs/zip.min.js
QianduanNeicanFix1/js/plugins/__init__.py
QianduanNeicanFix1/js/plugins/hypothesis.js
QianduanNeicanFix1/js/plugins/search.js
qianduan_neican_fix1-2025.3.25.0.dist-info/METADATA
qianduan_neican_fix1-2025.3.25.0.dist-info/WHEEL
qianduan_neican_fix1-2025.3.25.0.dist-info/entry_points.txt
qianduan_neican_fix1-2025.3.25.0.dist-info/top_level.txt
qianduan_neican_fix1-2025.3.25.0.dist-info/RECORD
